pydataassist/__init__.py
pydataassist/__main__.py
pydataassist/encryption.py
pydataassist/py.typed
pydataassist/restassist.py
pydataassist/sparkassist.py
pydataassist-0.1.1.dist-info/LICENSE
pydataassist-0.1.1.dist-info/METADATA
pydataassist-0.1.1.dist-info/WHEEL
pydataassist-0.1.1.dist-info/entry_points.txt
pydataassist-0.1.1.dist-info/RECORD
