Metadata-Version: 2.1
Name: pydataassist
Version: 0.1.1
Summary: PyDataUtils
Home-page: https://github.com/anilkulkarni87/pydatautils
License: MIT
Author: Anil Kulkarni
Author-email: anil77k@gmail.com
Requires-Python: >=3.7,<4.0
Classifier: Development Status :: 1 - Planning
Classifier: License :: OSI Approved :: MIT License
Classifier: Programming Language :: Python :: 3
Classifier: Programming Language :: Python :: 3.7
Classifier: Programming Language :: Python :: 3.8
Classifier: Programming Language :: Python :: 3.9
Classifier: Programming Language :: Python :: 3.10
Classifier: Programming Language :: Python :: 3.11
Requires-Dist: click (>=8.0.1)
Requires-Dist: pycryptodomex (>=3.17,<4.0)
Requires-Dist: pyspark (>=3.3.2,<4.0.0)
Requires-Dist: requests (>=2.28.2,<3.0.0)
Requires-Dist: types-requests (>=2.28.11.15,<3.0.0.0)
Project-URL: Changelog, https://github.com/anilkulkarni87/pydatautils/releases
Project-URL: Documentation, https://pydatautils.readthedocs.io
Project-URL: Repository, https://github.com/anilkulkarni87/pydatautils
